<?xml version="1.0" encoding="utf-8"?>
<content>
	<language>en</language>
	<site_name>Example documentation</site_name>
	<stylesheet_name>OldSchoolDocs</stylesheet_name>

	<introduction>
		<text>Welcome to the Example documentation!</text>
		<text><![CDATA[Here you can find various guides, or... you can open the <strong><a href=".htmldata/pages/template.html">Template Guide</a></strong> for reference.]]></text>
	</introduction>

	<guides>
		<category name="Generic" id="generic">
			<entry name="Template guide" filename="template" status="Complete" completeness="100%"></entry>
		</category>
	</guides>
</content>